<?xml version="1.0" encoding="utf-8" ?>
<UniversalEditor Version="4.0">
	<Associations>
		<Association>
			<Filters>
				<Filter Title="Polygon Movie Maker pose data">
					<FileNameFilters>
						<FileNameFilter>*.vpd</FileNameFilter>
					</FileNameFilters>
					<MagicByteSequences>
						<MagicByteSequence>
							<MagicByte Type="String">Vocaloid Pose Data file</MagicByte>
						</MagicByteSequence>
					</MagicByteSequences>
				</Filter>
			</Filters>
			<ObjectModels>
				<ObjectModel TypeName="UniversalEditor.ObjectModels.Multimedia3D.Scene.SceneObjectModel" />
			</ObjectModels>
			<DataFormats>
				<DataFormat TypeName="UniversalEditor.DataFormats.Multimedia3D.Pose.PolygonMovieMaker.VPDPoseDataFormat" />
			</DataFormats>
		</Association>
	</Associations>
</UniversalEditor>